cfxs_merge/__init__.py
cfxs_merge/merge.py
cfxs_merge-0.0.1.dist-info/METADATA
cfxs_merge-0.0.1.dist-info/WHEEL
cfxs_merge-0.0.1.dist-info/top_level.txt
cfxs_merge-0.0.1.dist-info/RECORD
