Metadata-Version: 2.1
Name: cfxs_merge
Version: 0.0.1
Summary: cfxs merge
Home-page: https://github.com/bitfugui/cfxs_merge
Author: bitfugui
Author-email: bitfugui@gmail.com
Classifier: Programming Language :: Python :: 3
Classifier: License :: OSI Approved :: MIT License
Classifier: Operating System :: OS Independent
Requires-Dist: web3 >=6.5.0
